LICENSE
MANIFEST.in
README.md
setup.py
amp/__init__.py
amp/apps.py
amp/middleware.py
amp/tests.py
amp/utils.py
amp/lib/transformer-darwin-10.6-amd64.dylib
amp/lib/transformer-darwin-10.6-amd64.h
amp/lib/transformer-linux-amd64.h
amp/lib/transformer-linux-amd64.so
amp/template/__init__.py
amp/template/backends/__init__.py
amp/template/backends/amp.py
amp/template/backends/utils.py
amp/templatetags/__init__.py
amp/templatetags/amp.py
django_canonical_amp.egg-info/PKG-INFO
django_canonical_amp.egg-info/SOURCES.txt
django_canonical_amp.egg-info/dependency_links.txt
django_canonical_amp.egg-info/requires.txt
django_canonical_amp.egg-info/top_level.txt