Metadata-Version: 2.1
Name: django-canonical-amp
Version: 0.1b0
Summary: Template tags and middlewares to build canonical AMP pages with Django easily.
Home-page: https://github.com/matthiasrohmer/django-amp
Author: Matthias Rohmer
Author-email: rohmer.matthias@anyvent.org
License: Apache License 2.0
Platform: UNKNOWN
Classifier: Environment :: Web Environment
Classifier: Framework :: Django
Classifier: Framework :: Django :: 2.1
Classifier: Intended Audience :: Developers
Classifier: License :: OSI Approved :: Apache Software License
Classifier: Operating System :: OS Independent
Classifier: Programming Language :: Python
Classifier: Programming Language :: Python :: 3.5
Classifier: Programming Language :: Python :: 3.6
Classifier: Topic :: Internet :: WWW/HTTP
Classifier: Topic :: Internet :: WWW/HTTP :: Dynamic Content
